podmaker/__init__.py
podmaker/__main__.py
podmaker/cli.py
podmaker/config/__init__.py
podmaker/config/core.py
podmaker/config/storage.py
podmaker/fetcher/__init__.py
podmaker/fetcher/core.py
podmaker/fetcher/youtube.py
podmaker/processor/__init__.py
podmaker/processor/core.py
podmaker/processor/scheduling.py
podmaker/processor/task.py
podmaker/rss/README.md
podmaker/rss/__init__.py
podmaker/rss/core.py
podmaker/rss/enclosure.py
podmaker/rss/episode.py
podmaker/rss/podcast.py
podmaker/rss/util/__init__.py
podmaker/rss/util/namespace.py
podmaker/rss/util/parse.py
podmaker/storage/__init__.py
podmaker/storage/core.py
podmaker/storage/local.py
podmaker/storage/s3.py
podmaker/util/__init__.py
podmaker/util/exit.py
podmaker/util/retry_util.py
podmaker-0.9.0.dist-info/LICENSE
podmaker-0.9.0.dist-info/METADATA
podmaker-0.9.0.dist-info/WHEEL
podmaker-0.9.0.dist-info/entry_points.txt
podmaker-0.9.0.dist-info/RECORD
