Metadata-Version: 2.1
Name: podmaker
Version: 0.9.0
Summary: Convert online media into podcast feeds.
Home-page: https://github.com/YogiLiu/podmaker
License: Unlicense
Keywords: rss,youtube,podcast
Author: YogiLiu
Author-email: YogiLiu@outlook.com
Maintainer: YogiLiu
Maintainer-email: YogiLiu@outlook.com
Requires-Python: >=3.9,<4.0
Classifier: Development Status :: 4 - Beta
Classifier: Environment :: Console
Classifier: License :: OSI Approved
Classifier: Programming Language :: Python :: 3
Classifier: Programming Language :: Python :: 3.9
Classifier: Programming Language :: Python :: 3.10
Classifier: Programming Language :: Python :: 3.11
Provides-Extra: all
Provides-Extra: s3
Provides-Extra: youtube
Requires-Dist: apscheduler (>=3.10.4,<4.0.0)
Requires-Dist: boto3 (>=1.28.27,<2.0.0) ; extra == "s3" or extra == "all"
Requires-Dist: pydantic[email] (>=2.2.0,<3.0.0)
Requires-Dist: tomlkit (>=0.12.1,<0.13.0)
Requires-Dist: yt-dlp (>=2023.7.6,<2024.0.0) ; extra == "youtube" or extra == "all"
Project-URL: Bug Tracker, https://github.com/YogiLiu/podmaker/issues
Project-URL: Documentation, https://github.com/YogiLiu/podmaker/blob/main/README.md
Project-URL: Repository, https://github.com/YogiLiu/podmaker
